{"created_at": "Tue Mar 19 14:10:32 +0000 2019", "id": 1108007852273225730, "id_str": "1108007852273225730", "full_text": "RT @XavierB36568183: Ma vid\u00e9o de l'acte 18. Partagez\n\n#GiletsJaunes #GiletJaune #giletsjaune #YellowVest #YellowJackets #Acte18 #acteXVII #\u2026", "truncated": false, "display_text_range": [0, 140], "entities": {"hashtags": [{"text": "GiletsJaunes", "indices": [54, 67]}, {"text": "GiletJaune", "indices": [68, 79]}, {"text": "giletsjaune", "indices": [80, 92]}, {"text": "YellowVest", "indices": [93, 104]}, {"text": "YellowJackets", "indices": [105, 119]}, {"text": "Acte18", "indices": [120, 127]}, {"text": "acteXVII", "indices": [128, 137]}], "symbols": [], "user_mentions": [{"screen_name": "XavierB36568183", "name": "Xavier B", "id": 1089888002187427843, "id_str": "1089888002187427843", "indices": [3, 19]}], "urls": []}, "metadata": {"iso_language_code": "fr", "result_type": "recent"}, "source": "<a href=\"http://twitter.com\" rel=\"nofollow\">Twitter Web Client</a>", "in_reply_to_status_id": null, "in_reply_to_status_id_str": null, "in_reply_to_user_id": null, "in_reply_to_user_id_str": null, "in_reply_to_screen_name": null, "user": {"id": 1438786232, "id_str": "1438786232", "name": "Di Lovero", "screen_name": "LoveroNicolas", "location": "France", "description": "Auteur, compositeur, interpr\u00e8te. Antifasciste, antilib\u00e9ral, humaniste, d\u00e9mocrate, la\u00efcard, https://t.co/nO0L8jrUfy", "url": "https://t.co/sjdYZp9MAE", "entities": {"url": {"urls": [{"url": "https://t.co/sjdYZp9MAE", "expanded_url": "https://www.youtube.com/watch?v=Ma0qFxBbpvI", "display_url": "youtube.com/watch?v=Ma0qFx\u2026", "indices": [0, 23]}]}, "description": {"urls": [{"url": "https://t.co/nO0L8jrUfy", "expanded_url": "https://soundcloud.com/nicolaslovero/marchercontrelevent", "display_url": "soundcloud.com/nicolaslovero/\u2026", "indices": [91, 114]}]}}, "protected": false, "followers_count": 2357, "friends_count": 4684, "listed_count": 57, "created_at": "Sat May 18 16:13:32 +0000 2013", "favourites_count": 3031, "utc_offset": null, "time_zone": null, "geo_enabled": false, "verified": false, "statuses_count": 10327, "lang": "fr", "contributors_enabled": false, "is_translator": false, "is_translation_enabled": false, "profile_background_color": "C0DEED", "profile_background_image_url": "http://abs.twimg.com/images/themes/theme1/bg.png", "profile_background_image_url_https": "https://abs.twimg.com/images/themes/theme1/bg.png", "profile_background_tile": false, "profile_image_url": "http://pbs.twimg.com/profile_images/1049215094087929856/kb4t43Zb_normal.jpg", "profile_image_url_https": "https://pbs.twimg.com/profile_images/1049215094087929856/kb4t43Zb_normal.jpg", "profile_banner_url": "https://pbs.twimg.com/profile_banners/1438786232/1540242847", "profile_link_color": "1631E0", "profile_sidebar_border_color": "C0DEED", "profile_sidebar_fill_color": "DDEEF6", "profile_text_color": "333333", "profile_use_background_image": true, "has_extended_profile": true, "default_profile": false, "default_profile_image": false, "following": false, "follow_request_sent": false, "notifications": false, "translator_type": "none"}, "geo": null, "coordinates": null, "place": null, "contributors": null, "retweeted_status": {"created_at": "Tue Mar 19 13:51:28 +0000 2019", "id": 1108003052412436480, "id_str": "1108003052412436480", "full_text": "Ma vid\u00e9o de l'acte 18. Partagez\n\n#GiletsJaunes #GiletJaune #giletsjaune #YellowVest #YellowJackets #Acte18 #acteXVII #CastanerChampion #casseurs #blackblocs #BlackBloc #ChampsElysees #Macron #16mars2019 #16Mars #manifestations #loianticasseurs\n\nhttps://t.co/cY65X0SJOy", "truncated": false, "display_text_range": [0, 268], "entities": {"hashtags": [{"text": "GiletsJaunes", "indices": [33, 46]}, {"text": "GiletJaune", "indices": [47, 58]}, {"text": "giletsjaune", "indices": [59, 71]}, {"text": "YellowVest", "indices": [72, 83]}, {"text": "YellowJackets", "indices": [84, 98]}, {"text": "Acte18", "indices": [99, 106]}, {"text": "acteXVII", "indices": [107, 116]}, {"text": "CastanerChampion", "indices": [117, 134]}, {"text": "casseurs", "indices": [135, 144]}, {"text": "blackblocs", "indices": [145, 156]}, {"text": "BlackBloc", "indices": [157, 167]}, {"text": "ChampsElysees", "indices": [168, 182]}, {"text": "Macron", "indices": [183, 190]}, {"text": "16mars2019", "indices": [191, 202]}, {"text": "16Mars", "indices": [203, 210]}, {"text": "manifestations", "indices": [211, 226]}, {"text": "loianticasseurs", "indices": [227, 243]}], "symbols": [], "user_mentions": [], "urls": [{"url": "https://t.co/cY65X0SJOy", "expanded_url": "https://youtu.be/fJ0XGfe0Oyw", "display_url": "youtu.be/fJ0XGfe0Oyw", "indices": [245, 268]}]}, "metadata": {"iso_language_code": "fr", "result_type": "recent"}, "source": "<a href=\"http://twitter.com/download/android\" rel=\"nofollow\">Twitter for Android</a>", "in_reply_to_status_id": null, "in_reply_to_status_id_str": null, "in_reply_to_user_id": null, "in_reply_to_user_id_str": null, "in_reply_to_screen_name": null, "user": {"id": 1089888002187427843, "id_str": "1089888002187427843", "name": "Xavier B", "screen_name": "XavierB36568183", "location": "", "description": "", "url": null, "entities": {"description": {"urls": []}}, "protected": false, "followers_count": 1, "friends_count": 10, "listed_count": 0, "created_at": "Mon Jan 28 14:08:43 +0000 2019", "favourites_count": 4, "utc_offset": null, "time_zone": null, "geo_enabled": false, "verified": false, "statuses_count": 5, "lang": "fr", "contributors_enabled": false, "is_translator": false, "is_translation_enabled": false, "profile_background_color": "F5F8FA", "profile_background_image_url": null, "profile_background_image_url_https": null, "profile_background_tile": false, "profile_image_url": "http://abs.twimg.com/sticky/default_profile_images/default_profile_normal.png", "profile_image_url_https": "https://abs.twimg.com/sticky/default_profile_images/default_profile_normal.png", "profile_link_color": "1DA1F2", "profile_sidebar_border_color": "C0DEED", "profile_sidebar_fill_color": "DDEEF6", "profile_text_color": "333333", "profile_use_background_image": true, "has_extended_profile": false, "default_profile": true, "default_profile_image": true, "following": false, "follow_request_sent": false, "notifications": false, "translator_type": "none"}, "geo": null, "coordinates": null, "place": null, "contributors": null, "is_quote_status": false, "retweet_count": 5, "favorite_count": 1, "favorited": false, "retweeted": false, "possibly_sensitive": false, "lang": "fr"}, "is_quote_status": false, "retweet_count": 5, "favorite_count": 0, "favorited": false, "retweeted": false, "possibly_sensitive": false, "lang": "fr"}