{"created_at": "Tue Mar 19 09:46:05 +0000 2019", "id": 1107941300433608705, "id_str": "1107941300433608705", "full_text": "#FAHRENHEIT451\nSEPT  KIOSQUES BR\u00dbL\u00c9S\n\n#GiletsJaunes font des selfies hilares devant le brasier.\nLe \"journaliste\" #EdwyPlenel : #GiletJaune ont compris que SEULE LA VIOLENCE PAYE.\nJourn petits bourgeois #FranceInter : un mvt social pendant que #Macron fait du ski\n@JeanLoupSalzman https://t.co/qBxRbHCJdu", "truncated": false, "display_text_range": [0, 279], "entities": {"hashtags": [{"text": "FAHRENHEIT451", "indices": [0, 14]}, {"text": "GiletsJaunes", "indices": [38, 51]}, {"text": "EdwyPlenel", "indices": [113, 124]}, {"text": "GiletJaune", "indices": [127, 138]}, {"text": "FranceInter", "indices": [202, 214]}, {"text": "Macron", "indices": [243, 250]}], "symbols": [], "user_mentions": [{"screen_name": "JeanLoupSalzman", "name": "Jean-Loup Salzmann", "id": 882280344, "id_str": "882280344", "indices": [263, 279]}], "urls": [{"url": "https://t.co/qBxRbHCJdu", "expanded_url": "https://twitter.com/bertrandgie/status/1107549661387202560", "display_url": "twitter.com/bertrandgie/st\u2026", "indices": [280, 303]}]}, "metadata": {"iso_language_code": "fr", "result_type": "recent"}, "source": "<a href=\"http://twitter.com/download/android\" rel=\"nofollow\">Twitter for Android</a>", "in_reply_to_status_id": null, "in_reply_to_status_id_str": null, "in_reply_to_user_id": null, "in_reply_to_user_id_str": null, "in_reply_to_screen_name": null, "user": {"id": 826378796823564288, "id_str": "826378796823564288", "name": "PatBoy", "screen_name": "pat7boy", "location": "", "description": "In Girum Imus Nocte Ecce et Consumimur Igni", "url": null, "entities": {"description": {"urls": []}}, "protected": false, "followers_count": 59, "friends_count": 95, "listed_count": 2, "created_at": "Tue Jan 31 10:37:13 +0000 2017", "favourites_count": 1442, "utc_offset": null, "time_zone": null, "geo_enabled": true, "verified": false, "statuses_count": 3193, "lang": "en", "contributors_enabled": false, "is_translator": false, "is_translation_enabled": false, "profile_background_color": "F5F8FA", "profile_background_image_url": null, "profile_background_image_url_https": null, "profile_background_tile": false, "profile_image_url": "http://pbs.twimg.com/profile_images/835517858062819328/kqdj_1yA_normal.jpg", "profile_image_url_https": "https://pbs.twimg.com/profile_images/835517858062819328/kqdj_1yA_normal.jpg", "profile_banner_url": "https://pbs.twimg.com/profile_banners/826378796823564288/1551177800", "profile_link_color": "1DA1F2", "profile_sidebar_border_color": "C0DEED", "profile_sidebar_fill_color": "DDEEF6", "profile_text_color": "333333", "profile_use_background_image": true, "has_extended_profile": false, "default_profile": true, "default_profile_image": false, "following": false, "follow_request_sent": false, "notifications": false, "translator_type": "none"}, "geo": null, "coordinates": null, "place": null, "contributors": null, "is_quote_status": true, "quoted_status_id": 1107549661387202560, "quoted_status_id_str": "1107549661387202560", "quoted_status": {"created_at": "Mon Mar 18 07:49:51 +0000 2019", "id": 1107549661387202560, "id_str": "1107549661387202560", "full_text": "Ce n est pas un mais SEPT kiosques qui ont \u00e9t\u00e9 br\u00fbl\u00e9s sur les Champs Elys\u00e9es samedi. https://t.co/ZItkMsjHTu", "truncated": false, "display_text_range": [0, 84], "entities": {"hashtags": [], "symbols": [], "user_mentions": [], "urls": [], "media": [{"id": 1107549625915969536, "id_str": "1107549625915969536", "indices": [85, 108], "media_url": "http://pbs.twimg.com/media/D17OhEfWkAAc_UK.jpg", "media_url_https": "https://pbs.twimg.com/media/D17OhEfWkAAc_UK.jpg", "url": "https://t.co/ZItkMsjHTu", "display_url": "pic.twitter.com/ZItkMsjHTu", "expanded_url": "https://twitter.com/bertrandgie/status/1107549661387202560/photo/1", "type": "photo", "sizes": {"medium": {"w": 900, "h": 1200, "resize": "fit"}, "thumb": {"w": 150, "h": 150, "resize": "crop"}, "large": {"w": 1536, "h": 2048, "resize": "fit"}, "small": {"w": 510, "h": 680, "resize": "fit"}}}]}, "extended_entities": {"media": [{"id": 1107549625915969536, "id_str": "1107549625915969536", "indices": [85, 108], "media_url": "http://pbs.twimg.com/media/D17OhEfWkAAc_UK.jpg", "media_url_https": "https://pbs.twimg.com/media/D17OhEfWkAAc_UK.jpg", "url": "https://t.co/ZItkMsjHTu", "display_url": "pic.twitter.com/ZItkMsjHTu", "expanded_url": "https://twitter.com/bertrandgie/status/1107549661387202560/photo/1", "type": "photo", "sizes": {"medium": {"w": 900, "h": 1200, "resize": "fit"}, "thumb": {"w": 150, "h": 150, "resize": "crop"}, "large": {"w": 1536, "h": 2048, "resize": "fit"}, "small": {"w": 510, "h": 680, "resize": "fit"}}}]}, "metadata": {"iso_language_code": "fr", "result_type": "recent"}, "source": "<a href=\"http://twitter.com/download/iphone\" rel=\"nofollow\">Twitter for iPhone</a>", "in_reply_to_status_id": null, "in_reply_to_status_id_str": null, "in_reply_to_user_id": null, "in_reply_to_user_id_str": null, "in_reply_to_screen_name": null, "user": {"id": 14665229, "id_str": "14665229", "name": "Bertrand Gi\u00e9", "screen_name": "bertrandgie", "location": "Paris, France", "description": "Directeur du Pole News @lefigaro (Le Figaro - https://t.co/gsUKfWgkaR - Le Figaro Magazine) & Pr\u00e9sident du @geste", "url": "https://t.co/7zSIokJk2k", "entities": {"url": {"urls": [{"url": "https://t.co/7zSIokJk2k", "expanded_url": "http://www.lefigaro.fr", "display_url": "lefigaro.fr", "indices": [0, 23]}]}, "description": {"urls": [{"url": "https://t.co/gsUKfWgkaR", "expanded_url": "http://lefigaro.fr", "display_url": "lefigaro.fr", "indices": [46, 69]}]}}, "protected": false, "followers_count": 2560, "friends_count": 1155, "listed_count": 60, "created_at": "Mon May 05 21:30:42 +0000 2008", "favourites_count": 3127, "utc_offset": null, "time_zone": null, "geo_enabled": true, "verified": true, "statuses_count": 2267, "lang": "fr", "contributors_enabled": false, "is_translator": false, "is_translation_enabled": false, "profile_background_color": "000000", "profile_background_image_url": "http://abs.twimg.com/images/themes/theme1/bg.png", "profile_background_image_url_https": "https://abs.twimg.com/images/themes/theme1/bg.png", "profile_background_tile": false, "profile_image_url": "http://pbs.twimg.com/profile_images/534099398327042048/o8dOLjuM_normal.jpeg", "profile_image_url_https": "https://pbs.twimg.com/profile_images/534099398327042048/o8dOLjuM_normal.jpeg", "profile_banner_url": "https://pbs.twimg.com/profile_banners/14665229/1498556932", "profile_link_color": "1B95E0", "profile_sidebar_border_color": "000000", "profile_sidebar_fill_color": "000000", "profile_text_color": "000000", "profile_use_background_image": false, "has_extended_profile": true, "default_profile": false, "default_profile_image": false, "following": false, "follow_request_sent": false, "notifications": false, "translator_type": "none"}, "geo": null, "coordinates": null, "place": {"id": "09f6a7707f18e0b1", "url": "https://api.twitter.com/1.1/geo/id/09f6a7707f18e0b1.json", "place_type": "city", "name": "Paris", "full_name": "Paris, France", "country_code": "FR", "country": "France", "contained_within": [], "bounding_box": {"type": "Polygon", "coordinates": [[[2.2241006, 48.8155214], [2.4699053, 48.8155214], [2.4699053, 48.9021461], [2.2241006, 48.9021461]]]}, "attributes": {}}, "contributors": null, "is_quote_status": false, "retweet_count": 119, "favorite_count": 131, "favorited": false, "retweeted": false, "possibly_sensitive": false, "lang": "fr"}, "retweet_count": 0, "favorite_count": 2, "favorited": false, "retweeted": false, "possibly_sensitive": false, "lang": "fr"}