{"created_at": "Fri Mar 29 08:53:47 +0000 2019", "id": 1111552017061814272, "id_str": "1111552017061814272", "full_text": "RT @Tobetwitt: #ActeXX #Flyrider #GiletJaune \nTiens au fait @FlyRiderGj toujours en France finalement? \nCa va tu ne portes pas trop tes cou\u2026", "truncated": false, "display_text_range": [0, 140], "entities": {"hashtags": [{"text": "ActeXX", "indices": [15, 22]}, {"text": "Flyrider", "indices": [23, 32]}, {"text": "GiletJaune", "indices": [33, 44]}], "symbols": [], "user_mentions": [{"screen_name": "Tobetwitt", "name": "Tobetwitt", "id": 1410305460, "id_str": "1410305460", "indices": [3, 13]}, {"screen_name": "FlyRiderGj", "name": "Maxime Nicolle (Fly Rider) officiel", "id": 149539920, "id_str": "149539920", "indices": [60, 71]}], "urls": []}, "metadata": {"iso_language_code": "fr", "result_type": "recent"}, "source": "<a href=\"http://twitter.com\" rel=\"nofollow\">Twitter Web Client</a>", "in_reply_to_status_id": null, "in_reply_to_status_id_str": null, "in_reply_to_user_id": null, "in_reply_to_user_id_str": null, "in_reply_to_screen_name": null, "user": {"id": 700649116611670016, "id_str": "700649116611670016", "name": "Vincent Lepage \ud83d\udd3b #RenaissanceEurop\u00e9enne", "screen_name": "VLAuteur", "location": "France", "description": "Militant #EnMarche depuis septembre 2016. \ud83d\udd8a\ufe0f\ud83c\uddeb\ud83c\uddf7\ud83c\uddea\ud83c\uddfa\ud83c\udff3\ufe0f\u200d\ud83c\udf08\ud83c\uddee\ud83c\uddf1#FBPE #StopGiletsJaunes #2QT2BSTR8 #JeVoteLe26mai #RenaissanceEurop\u00e9enne", "url": "https://t.co/g9J4dXJFVy", "entities": {"url": {"urls": [{"url": "https://t.co/g9J4dXJFVy", "expanded_url": "https://en-marche.fr", "display_url": "en-marche.fr", "indices": [0, 23]}]}, "description": {"urls": []}}, "protected": false, "followers_count": 5135, "friends_count": 4157, "listed_count": 5, "created_at": "Fri Feb 19 11:52:21 +0000 2016", "favourites_count": 42227, "utc_offset": null, "time_zone": null, "geo_enabled": false, "verified": false, "statuses_count": 19080, "lang": "fr", "contributors_enabled": false, "is_translator": false, "is_translation_enabled": false, "profile_background_color": "272727", "profile_background_image_url": "http://abs.twimg.com/images/themes/theme1/bg.png", "profile_background_image_url_https": "https://abs.twimg.com/images/themes/theme1/bg.png", "profile_background_tile": false, "profile_image_url": "http://pbs.twimg.com/profile_images/1097922299645362176/ff7Xwo4p_normal.png", "profile_image_url_https": "https://pbs.twimg.com/profile_images/1097922299645362176/ff7Xwo4p_normal.png", "profile_banner_url": "https://pbs.twimg.com/profile_banners/700649116611670016/1553225870", "profile_link_color": "003B6F", "profile_sidebar_border_color": "000000", "profile_sidebar_fill_color": "000000", "profile_text_color": "000000", "profile_use_background_image": false, "has_extended_profile": true, "default_profile": false, "default_profile_image": false, "following": false, "follow_request_sent": false, "notifications": false, "translator_type": "none"}, "geo": null, "coordinates": null, "place": null, "contributors": null, "retweeted_status": {"created_at": "Fri Mar 29 08:51:41 +0000 2019", "id": 1111551490395721728, "id_str": "1111551490395721728", "full_text": "#ActeXX #Flyrider #GiletJaune \nTiens au fait @FlyRiderGj toujours en France finalement? \nCa va tu ne portes pas trop tes couilles, c'est pas trop fatiguant? \nTu ne prends pas les gens pour des cons? du tout ???? https://t.co/apdp1pDV5p", "truncated": false, "display_text_range": [0, 211], "entities": {"hashtags": [{"text": "ActeXX", "indices": [0, 7]}, {"text": "Flyrider", "indices": [8, 17]}, {"text": "GiletJaune", "indices": [18, 29]}], "symbols": [], "user_mentions": [{"screen_name": "FlyRiderGj", "name": "Maxime Nicolle (Fly Rider) officiel", "id": 149539920, "id_str": "149539920", "indices": [45, 56]}], "urls": [], "media": [{"id": 1111551372732841984, "id_str": "1111551372732841984", "indices": [212, 235], "media_url": "http://pbs.twimg.com/media/D20GFZFWwAAqXy2.jpg", "media_url_https": "https://pbs.twimg.com/media/D20GFZFWwAAqXy2.jpg", "url": "https://t.co/apdp1pDV5p", "display_url": "pic.twitter.com/apdp1pDV5p", "expanded_url": "https://twitter.com/Tobetwitt/status/1111551490395721728/photo/1", "type": "photo", "sizes": {"thumb": {"w": 150, "h": 150, "resize": "crop"}, "large": {"w": 1084, "h": 733, "resize": "fit"}, "medium": {"w": 1084, "h": 733, "resize": "fit"}, "small": {"w": 680, "h": 460, "resize": "fit"}}}]}, "extended_entities": {"media": [{"id": 1111551372732841984, "id_str": "1111551372732841984", "indices": [212, 235], "media_url": "http://pbs.twimg.com/media/D20GFZFWwAAqXy2.jpg", "media_url_https": "https://pbs.twimg.com/media/D20GFZFWwAAqXy2.jpg", "url": "https://t.co/apdp1pDV5p", "display_url": "pic.twitter.com/apdp1pDV5p", "expanded_url": "https://twitter.com/Tobetwitt/status/1111551490395721728/photo/1", "type": "photo", "sizes": {"thumb": {"w": 150, "h": 150, "resize": "crop"}, "large": {"w": 1084, "h": 733, "resize": "fit"}, "medium": {"w": 1084, "h": 733, "resize": "fit"}, "small": {"w": 680, "h": 460, "resize": "fit"}}}]}, "metadata": {"iso_language_code": "fr", "result_type": "recent"}, "source": "<a href=\"http://twitter.com\" rel=\"nofollow\">Twitter Web Client</a>", "in_reply_to_status_id": null, "in_reply_to_status_id_str": null, "in_reply_to_user_id": null, "in_reply_to_user_id_str": null, "in_reply_to_screen_name": null, "user": {"id": 1410305460, "id_str": "1410305460", "name": "Tobetwitt", "screen_name": "Tobetwitt", "location": "Paris", "description": "Serial matriarcal motherfucker, Bitraillette, Mototaf , Monoparentalit\u00e9, n'aime pas les ISMES et les ISTES Je suis un TROLL, et MA PERSONNE EST SACREE !", "url": null, "entities": {"description": {"urls": []}}, "protected": false, "followers_count": 442, "friends_count": 303, "listed_count": 37, "created_at": "Tue May 07 14:03:40 +0000 2013", "favourites_count": 20923, "utc_offset": null, "time_zone": null, "geo_enabled": false, "verified": false, "statuses_count": 25171, "lang": "fr", "contributors_enabled": false, "is_translator": false, "is_translation_enabled": false, "profile_background_color": "C0DEED", "profile_background_image_url": "http://abs.twimg.com/images/themes/theme1/bg.png", "profile_background_image_url_https": "https://abs.twimg.com/images/themes/theme1/bg.png", "profile_background_tile": false, "profile_image_url": "http://pbs.twimg.com/profile_images/976457291733131266/4uB463rj_normal.jpg", "profile_image_url_https": "https://pbs.twimg.com/profile_images/976457291733131266/4uB463rj_normal.jpg", "profile_banner_url": "https://pbs.twimg.com/profile_banners/1410305460/1541424336", "profile_link_color": "1DA1F2", "profile_sidebar_border_color": "C0DEED", "profile_sidebar_fill_color": "DDEEF6", "profile_text_color": "333333", "profile_use_background_image": true, "has_extended_profile": false, "default_profile": true, "default_profile_image": false, "following": false, "follow_request_sent": false, "notifications": false, "translator_type": "none"}, "geo": null, "coordinates": null, "place": null, "contributors": null, "is_quote_status": false, "retweet_count": 2, "favorite_count": 6, "favorited": false, "retweeted": false, "possibly_sensitive": false, "lang": "fr"}, "is_quote_status": false, "retweet_count": 2, "favorite_count": 0, "favorited": false, "retweeted": false, "lang": "fr"}