{"created_at": "Thu Mar 28 15:18:21 +0000 2019", "id": 1111286409799843840, "id_str": "1111286409799843840", "full_text": "@BaabyxDoll @TPMP Je suis #giletjaune, chef d'entreprise et je gagne probablement bien + d'argent que toi, je travaille 80h/sem et je cr\u00e9\u00e9 de l'emploi. Tu reste les fesses sur ton canap\u00e9 entre 2 sorties shopping, pendant que je me soucis des autres et je me bat pour ceux qui ont moins. Tais toi.", "truncated": false, "display_text_range": [18, 296], "entities": {"hashtags": [{"text": "giletjaune", "indices": [26, 37]}], "symbols": [], "user_mentions": [{"screen_name": "BaabyxDoll", "name": "Mily Doll \u25e2 \u25e4", "id": 564917711, "id_str": "564917711", "indices": [0, 11]}, {"screen_name": "TPMP", "name": "TPMP", "id": 832766641, "id_str": "832766641", "indices": [12, 17]}], "urls": []}, "metadata": {"iso_language_code": "fr", "result_type": "recent"}, "source": "<a href=\"http://twitter.com\" rel=\"nofollow\">Twitter Web Client</a>", "in_reply_to_status_id": 1105921420184440832, "in_reply_to_status_id_str": "1105921420184440832", "in_reply_to_user_id": 564917711, "in_reply_to_user_id_str": "564917711", "in_reply_to_screen_name": "BaabyxDoll", "user": {"id": 2220071966, "id_str": "2220071966", "name": "rbin brdet", "screen_name": "RbinB", "location": "", "description": "", "url": null, "entities": {"description": {"urls": []}}, "protected": false, "followers_count": 36, "friends_count": 34, "listed_count": 1, "created_at": "Thu Nov 28 17:10:08 +0000 2013", "favourites_count": 257, "utc_offset": null, "time_zone": null, "geo_enabled": false, "verified": false, "statuses_count": 1039, "lang": "fr", "contributors_enabled": false, "is_translator": false, "is_translation_enabled": false, "profile_background_color": "C0DEED", "profile_background_image_url": "http://abs.twimg.com/images/themes/theme1/bg.png", "profile_background_image_url_https": "https://abs.twimg.com/images/themes/theme1/bg.png", "profile_background_tile": false, "profile_image_url": "http://pbs.twimg.com/profile_images/1110820506922614784/vz1Sl7gV_normal.png", "profile_image_url_https": "https://pbs.twimg.com/profile_images/1110820506922614784/vz1Sl7gV_normal.png", "profile_link_color": "1DA1F2", "profile_sidebar_border_color": "C0DEED", "profile_sidebar_fill_color": "DDEEF6", "profile_text_color": "333333", "profile_use_background_image": true, "has_extended_profile": false, "default_profile": true, "default_profile_image": false, "following": false, "follow_request_sent": false, "notifications": false, "translator_type": "regular"}, "geo": null, "coordinates": null, "place": null, "contributors": null, "is_quote_status": false, "retweet_count": 0, "favorite_count": 0, "favorited": false, "retweeted": false, "lang": "fr"}