{"created_at": "Tue Mar 26 20:33:37 +0000 2019", "id": 1110640974739447808, "id_str": "1110640974739447808", "full_text": "RT @GiletsJaunesFr: Cette apr\u00e8s-midi les Gilets Jaunes de Berlin manifestaient aussi. On pouvait lire au bas d'un gilet : \"Salutations patr\u2026", "truncated": false, "display_text_range": [0, 140], "entities": {"hashtags": [], "symbols": [], "user_mentions": [{"screen_name": "GiletsJaunesFr", "name": "LesGiletsJaunes.fr", "id": 1028668294751039488, "id_str": "1028668294751039488", "indices": [3, 18]}], "urls": []}, "metadata": {"iso_language_code": "fr", "result_type": "recent"}, "source": "<a href=\"http://twitter.com\" rel=\"nofollow\">Twitter Web Client</a>", "in_reply_to_status_id": null, "in_reply_to_status_id_str": null, "in_reply_to_user_id": null, "in_reply_to_user_id_str": null, "in_reply_to_screen_name": null, "user": {"id": 572612829, "id_str": "572612829", "name": "Serge T", "screen_name": "sergetokat", "location": "", "description": "Reconnaissance du G\u00e9nocide Arm\u00e9nien perp\u00e9tr\u00e9 par le Gvt Turc de 1915, ni\u00e9 par tous les autres. De Gauche #FH", "url": null, "entities": {"description": {"urls": []}}, "protected": false, "followers_count": 1668, "friends_count": 1223, "listed_count": 69, "created_at": "Sun May 06 11:16:36 +0000 2012", "favourites_count": 11353, "utc_offset": null, "time_zone": null, "geo_enabled": false, "verified": false, "statuses_count": 36781, "lang": "fr", "contributors_enabled": false, "is_translator": false, "is_translation_enabled": false, "profile_background_color": "C0DEED", "profile_background_image_url": "http://abs.twimg.com/images/themes/theme1/bg.png", "profile_background_image_url_https": "https://abs.twimg.com/images/themes/theme1/bg.png", "profile_background_tile": false, "profile_image_url": "http://pbs.twimg.com/profile_images/1064192613690089472/N4LjR8wo_normal.jpg", "profile_image_url_https": "https://pbs.twimg.com/profile_images/1064192613690089472/N4LjR8wo_normal.jpg", "profile_banner_url": "https://pbs.twimg.com/profile_banners/572612829/1545154297", "profile_link_color": "1DA1F2", "profile_sidebar_border_color": "C0DEED", "profile_sidebar_fill_color": "DDEEF6", "profile_text_color": "333333", "profile_use_background_image": true, "has_extended_profile": true, "default_profile": true, "default_profile_image": false, "following": false, "follow_request_sent": false, "notifications": false, "translator_type": "none"}, "geo": null, "coordinates": null, "place": null, "contributors": null, "retweeted_status": {"created_at": "Sat Mar 23 20:38:51 +0000 2019", "id": 1109555127726288896, "id_str": "1109555127726288896", "full_text": "Cette apr\u00e8s-midi les Gilets Jaunes de Berlin manifestaient aussi. On pouvait lire au bas d'un gilet : \"Salutations patriotiques \u00e0 la France\"\nhttps://t.co/AvuXF4jHyK\nIls ont adopt\u00e9 l'\u00e9tendard GJ :\nhttps://t.co/4C2C82mwjn\n#GiletJaune #YellowVests #chalecosamarillos #Gelbewesten https://t.co/DQij4ufit8", "truncated": false, "display_text_range": [0, 276], "entities": {"hashtags": [{"text": "GiletJaune", "indices": [220, 231]}, {"text": "YellowVests", "indices": [232, 244]}, {"text": "chalecosamarillos", "indices": [245, 263]}, {"text": "Gelbewesten", "indices": [264, 276]}], "symbols": [], "user_mentions": [], "urls": [{"url": "https://t.co/AvuXF4jHyK", "expanded_url": "https://www.facebook.com/Gelbewestenberlin/videos/410097366220010/", "display_url": "facebook.com/Gelbewestenber\u2026", "indices": [141, 164]}, {"url": "https://t.co/4C2C82mwjn", "expanded_url": "http://lesgiletsjaunes.fr/etendard-gilets-jaunes-europe/", "display_url": "lesgiletsjaunes.fr/etendard-gilet\u2026", "indices": [196, 219]}], "media": [{"id": 1109554831130271744, "id_str": "1109554831130271744", "indices": [277, 300], "media_url": "http://pbs.twimg.com/media/D2XuPYBWoAACTIm.jpg", "media_url_https": "https://pbs.twimg.com/media/D2XuPYBWoAACTIm.jpg", "url": "https://t.co/DQij4ufit8", "display_url": "pic.twitter.com/DQij4ufit8", "expanded_url": "https://twitter.com/GiletsJaunesFr/status/1109555127726288896/photo/1", "type": "photo", "sizes": {"thumb": {"w": 150, "h": 150, "resize": "crop"}, "large": {"w": 604, "h": 913, "resize": "fit"}, "medium": {"w": 604, "h": 913, "resize": "fit"}, "small": {"w": 450, "h": 680, "resize": "fit"}}}]}, "extended_entities": {"media": [{"id": 1109554831130271744, "id_str": "1109554831130271744", "indices": [277, 300], "media_url": "http://pbs.twimg.com/media/D2XuPYBWoAACTIm.jpg", "media_url_https": "https://pbs.twimg.com/media/D2XuPYBWoAACTIm.jpg", "url": "https://t.co/DQij4ufit8", "display_url": "pic.twitter.com/DQij4ufit8", "expanded_url": "https://twitter.com/GiletsJaunesFr/status/1109555127726288896/photo/1", "type": "photo", "sizes": {"thumb": {"w": 150, "h": 150, "resize": "crop"}, "large": {"w": 604, "h": 913, "resize": "fit"}, "medium": {"w": 604, "h": 913, "resize": "fit"}, "small": {"w": 450, "h": 680, "resize": "fit"}}}, {"id": 1109554842928857088, "id_str": "1109554842928857088", "indices": [277, 300], "media_url": "http://pbs.twimg.com/media/D2XuQD-WwAAJfHF.jpg", "media_url_https": "https://pbs.twimg.com/media/D2XuQD-WwAAJfHF.jpg", "url": "https://t.co/DQij4ufit8", "display_url": "pic.twitter.com/DQij4ufit8", "expanded_url": "https://twitter.com/GiletsJaunesFr/status/1109555127726288896/photo/1", "type": "photo", "sizes": {"thumb": {"w": 150, "h": 150, "resize": "crop"}, "medium": {"w": 750, "h": 470, "resize": "fit"}, "small": {"w": 680, "h": 426, "resize": "fit"}, "large": {"w": 750, "h": 470, "resize": "fit"}}}, {"id": 1109554850734530560, "id_str": "1109554850734530560", "indices": [277, 300], "media_url": "http://pbs.twimg.com/media/D2XuQhDX4AA3IE7.jpg", "media_url_https": "https://pbs.twimg.com/media/D2XuQhDX4AA3IE7.jpg", "url": "https://t.co/DQij4ufit8", "display_url": "pic.twitter.com/DQij4ufit8", "expanded_url": "https://twitter.com/GiletsJaunesFr/status/1109555127726288896/photo/1", "type": "photo", "sizes": {"small": {"w": 680, "h": 330, "resize": "fit"}, "thumb": {"w": 150, "h": 150, "resize": "crop"}, "medium": {"w": 960, "h": 466, "resize": "fit"}, "large": {"w": 960, "h": 466, "resize": "fit"}}}]}, "metadata": {"iso_language_code": "fr", "result_type": "recent"}, "source": "<a href=\"http://twitter.com\" rel=\"nofollow\">Twitter Web Client</a>", "in_reply_to_status_id": null, "in_reply_to_status_id_str": null, "in_reply_to_user_id": null, "in_reply_to_user_id_str": null, "in_reply_to_screen_name": null, "user": {"id": 1028668294751039488, "id_str": "1028668294751039488", "name": "LesGiletsJaunes.fr", "screen_name": "GiletsJaunesFr", "location": "", "description": "Mouvement citoyen apartisan pour une d\u00e9mocratie d'avenir. #GiletJaune #GiletsJaunes #RIC", "url": "https://t.co/6L8a9X18Kn", "entities": {"url": {"urls": [{"url": "https://t.co/6L8a9X18Kn", "expanded_url": "http://lesgiletsjaunes.fr/", "display_url": "lesgiletsjaunes.fr", "indices": [0, 23]}]}, "description": {"urls": []}}, "protected": false, "followers_count": 28825, "friends_count": 0, "listed_count": 146, "created_at": "Sun Aug 12 15:43:27 +0000 2018", "favourites_count": 0, "utc_offset": null, "time_zone": null, "geo_enabled": false, "verified": false, "statuses_count": 603, "lang": "fr", "contributors_enabled": false, "is_translator": false, "is_translation_enabled": false, "profile_background_color": "000000", "profile_background_image_url": "http://abs.twimg.com/images/themes/theme1/bg.png", "profile_background_image_url_https": "https://abs.twimg.com/images/themes/theme1/bg.png", "profile_background_tile": false, "profile_image_url": "http://pbs.twimg.com/profile_images/1061768312001048576/a12UuwLu_normal.jpg", "profile_image_url_https": "https://pbs.twimg.com/profile_images/1061768312001048576/a12UuwLu_normal.jpg", "profile_banner_url": "https://pbs.twimg.com/profile_banners/1028668294751039488/1547516729", "profile_link_color": "FEF100", "profile_sidebar_border_color": "000000", "profile_sidebar_fill_color": "000000", "profile_text_color": "000000", "profile_use_background_image": false, "has_extended_profile": true, "default_profile": false, "default_profile_image": false, "following": false, "follow_request_sent": false, "notifications": false, "translator_type": "none"}, "geo": null, "coordinates": null, "place": null, "contributors": null, "is_quote_status": false, "retweet_count": 108, "favorite_count": 149, "favorited": false, "retweeted": false, "possibly_sensitive": false, "lang": "fr"}, "is_quote_status": false, "retweet_count": 108, "favorite_count": 0, "favorited": false, "retweeted": false, "lang": "fr"}