{"created_at": "Mon Mar 18 22:44:04 +0000 2019", "id": 1107774697968750592, "id_str": "1107774697968750592", "full_text": "RT @Dondraper100791: #ActeXVIII . Un #GiletJaune \"on en a marre d'\u00eatre l\u00e0\". \n\nBen \u00e7a tombe bien, Jojo, parce que vos tronches, on les a ass\u2026", "truncated": false, "display_text_range": [0, 140], "entities": {"hashtags": [{"text": "ActeXVIII", "indices": [21, 31]}, {"text": "GiletJaune", "indices": [37, 48]}], "symbols": [], "user_mentions": [{"screen_name": "Dondraper100791", "name": "Dondraper1007", "id": 902493595671912448, "id_str": "902493595671912448", "indices": [3, 19]}], "urls": []}, "metadata": {"iso_language_code": "fr", "result_type": "recent"}, "source": "<a href=\"https://twitter.com/ForceCollectiv\" rel=\"nofollow\">Retwitteuse</a>", "in_reply_to_status_id": null, "in_reply_to_status_id_str": null, "in_reply_to_user_id": null, "in_reply_to_user_id_str": null, "in_reply_to_screen_name": null, "user": {"id": 1024647535661600768, "id_str": "1024647535661600768", "name": "Politique4.0#10\ud83c\udde7\ud83c\uddea\ud83c\uddeb\ud83c\uddf7\ud83c\uddee\ud83c\uddf9", "screen_name": "DuPouvoirDachat", "location": "9 millions de pauvres qui se r\u00e9veillent...", "description": "Ne supporte plus de voir des personnes sous le seuil de pauvret\u00e9. 9 millions de pauvres? @Obs_Violences #LCIdirect #LCI #La26 Soutien aux #GiletsJaunes rt.", "url": null, "entities": {"description": {"urls": []}}, "protected": false, "followers_count": 3489, "friends_count": 1998, "listed_count": 35, "created_at": "Wed Aug 01 13:26:24 +0000 2018", "favourites_count": 7774, "utc_offset": null, "time_zone": null, "geo_enabled": false, "verified": false, "statuses_count": 220253, "lang": "fr", "contributors_enabled": false, "is_translator": false, "is_translation_enabled": false, "profile_background_color": "000000", "profile_background_image_url": "http://abs.twimg.com/images/themes/theme1/bg.png", "profile_background_image_url_https": "https://abs.twimg.com/images/themes/theme1/bg.png", "profile_background_tile": false, "profile_image_url": "http://pbs.twimg.com/profile_images/1069651828869083136/FW_oMeYV_normal.jpg", "profile_image_url_https": "https://pbs.twimg.com/profile_images/1069651828869083136/FW_oMeYV_normal.jpg", "profile_banner_url": "https://pbs.twimg.com/profile_banners/1024647535661600768/1552939385", "profile_link_color": "F3ED00", "profile_sidebar_border_color": "000000", "profile_sidebar_fill_color": "000000", "profile_text_color": "000000", "profile_use_background_image": false, "has_extended_profile": true, "default_profile": false, "default_profile_image": false, "following": false, "follow_request_sent": false, "notifications": false, "translator_type": "none"}, "geo": null, "coordinates": null, "place": null, "contributors": null, "retweeted_status": {"created_at": "Mon Mar 18 22:43:27 +0000 2019", "id": 1107774545124044800, "id_str": "1107774545124044800", "full_text": "#ActeXVIII . Un #GiletJaune \"on en a marre d'\u00eatre l\u00e0\". \n\nBen \u00e7a tombe bien, Jojo, parce que vos tronches, on les a assez vues, aussi.\nTu vois ce que je veux dire? https://t.co/vBLUYDnHkD", "truncated": false, "display_text_range": [0, 162], "entities": {"hashtags": [{"text": "ActeXVIII", "indices": [0, 10]}, {"text": "GiletJaune", "indices": [16, 27]}], "symbols": [], "user_mentions": [], "urls": [], "media": [{"id": 1107774509661241345, "id_str": "1107774509661241345", "indices": [163, 186], "media_url": "http://pbs.twimg.com/media/D1-bDBuXQAEJJlq.png", "media_url_https": "https://pbs.twimg.com/media/D1-bDBuXQAEJJlq.png", "url": "https://t.co/vBLUYDnHkD", "display_url": "pic.twitter.com/vBLUYDnHkD", "expanded_url": "https://twitter.com/Dondraper100791/status/1107774545124044800/photo/1", "type": "photo", "sizes": {"large": {"w": 571, "h": 554, "resize": "fit"}, "small": {"w": 571, "h": 554, "resize": "fit"}, "medium": {"w": 571, "h": 554, "resize": "fit"}, "thumb": {"w": 150, "h": 150, "resize": "crop"}}}]}, "extended_entities": {"media": [{"id": 1107774509661241345, "id_str": "1107774509661241345", "indices": [163, 186], "media_url": "http://pbs.twimg.com/media/D1-bDBuXQAEJJlq.png", "media_url_https": "https://pbs.twimg.com/media/D1-bDBuXQAEJJlq.png", "url": "https://t.co/vBLUYDnHkD", "display_url": "pic.twitter.com/vBLUYDnHkD", "expanded_url": "https://twitter.com/Dondraper100791/status/1107774545124044800/photo/1", "type": "photo", "sizes": {"large": {"w": 571, "h": 554, "resize": "fit"}, "small": {"w": 571, "h": 554, "resize": "fit"}, "medium": {"w": 571, "h": 554, "resize": "fit"}, "thumb": {"w": 150, "h": 150, "resize": "crop"}}}]}, "metadata": {"iso_language_code": "fr", "result_type": "recent"}, "source": "<a href=\"http://twitter.com\" rel=\"nofollow\">Twitter Web Client</a>", "in_reply_to_status_id": null, "in_reply_to_status_id_str": null, "in_reply_to_user_id": null, "in_reply_to_user_id_str": null, "in_reply_to_screen_name": null, "user": {"id": 902493595671912448, "id_str": "902493595671912448", "name": "Dondraper1007", "screen_name": "Dondraper100791", "location": "New York, NY", "description": "Publicitaire. Je bois du whisky, je fume sans filtres, et je fais des siestes au bureau.", "url": null, "entities": {"description": {"urls": []}}, "protected": false, "followers_count": 773, "friends_count": 669, "listed_count": 4, "created_at": "Tue Aug 29 11:30:15 +0000 2017", "favourites_count": 1808, "utc_offset": null, "time_zone": null, "geo_enabled": false, "verified": false, "statuses_count": 2375, "lang": "fr", "contributors_enabled": false, "is_translator": false, "is_translation_enabled": false, "profile_background_color": "F5F8FA", "profile_background_image_url": null, "profile_background_image_url_https": null, "profile_background_tile": false, "profile_image_url": "http://pbs.twimg.com/profile_images/902502570559774720/pI5msLor_normal.jpg", "profile_image_url_https": "https://pbs.twimg.com/profile_images/902502570559774720/pI5msLor_normal.jpg", "profile_banner_url": "https://pbs.twimg.com/profile_banners/902493595671912448/1504008893", "profile_link_color": "1DA1F2", "profile_sidebar_border_color": "C0DEED", "profile_sidebar_fill_color": "DDEEF6", "profile_text_color": "333333", "profile_use_background_image": true, "has_extended_profile": false, "default_profile": true, "default_profile_image": false, "following": false, "follow_request_sent": false, "notifications": false, "translator_type": "none"}, "geo": null, "coordinates": null, "place": null, "contributors": null, "is_quote_status": false, "retweet_count": 3, "favorite_count": 7, "favorited": false, "retweeted": false, "possibly_sensitive": false, "lang": "fr"}, "is_quote_status": false, "retweet_count": 3, "favorite_count": 0, "favorited": false, "retweeted": false, "lang": "fr"}