{"created_at": "Tue Mar 19 07:47:59 +0000 2019", "id": 1107911582527512578, "id_str": "1107911582527512578", "full_text": "RT @actu_phone: INFORMATION EUROPE 1 : le domicile du \"#giletjaune\" #\u00c9ric Drouet vandalis\u00e9 https://t.co/rZvy2mgcuj", "truncated": false, "display_text_range": [0, 114], "entities": {"hashtags": [{"text": "giletjaune", "indices": [55, 66]}, {"text": "\u00c9ric", "indices": [68, 73]}], "symbols": [], "user_mentions": [{"screen_name": "actu_phone", "name": "\ud83c\udf0e ActuWorld \ud83c\udf0d", "id": 1043410125774626816, "id_str": "1043410125774626816", "indices": [3, 14]}], "urls": [{"url": "https://t.co/rZvy2mgcuj", "expanded_url": "https://www.europe1.fr/faits-divers/information-europe-1-le-domicile-du-gilet-jaune-eric-drouet-vandalise-3876593", "display_url": "europe1.fr/faits-divers/i\u2026", "indices": [91, 114]}]}, "metadata": {"iso_language_code": "fr", "result_type": "recent"}, "source": "<a href=\"http://twitter.com/download/iphone\" rel=\"nofollow\">Twitter for iPhone</a>", "in_reply_to_status_id": null, "in_reply_to_status_id_str": null, "in_reply_to_user_id": null, "in_reply_to_user_id_str": null, "in_reply_to_screen_name": null, "user": {"id": 892096112026427392, "id_str": "892096112026427392", "name": "Victoria", "screen_name": "Victoria06800", "location": "Ile-de-France, France", "description": "Bla bla bla \ud83d\ude1c", "url": null, "entities": {"description": {"urls": []}}, "protected": false, "followers_count": 109, "friends_count": 128, "listed_count": 0, "created_at": "Mon Jul 31 18:54:22 +0000 2017", "favourites_count": 1102, "utc_offset": null, "time_zone": null, "geo_enabled": false, "verified": false, "statuses_count": 1451, "lang": "fr", "contributors_enabled": false, "is_translator": false, "is_translation_enabled": false, "profile_background_color": "F5F8FA", "profile_background_image_url": null, "profile_background_image_url_https": null, "profile_background_tile": false, "profile_image_url": "http://pbs.twimg.com/profile_images/892099455792623616/BE1Q9mSA_normal.jpg", "profile_image_url_https": "https://pbs.twimg.com/profile_images/892099455792623616/BE1Q9mSA_normal.jpg", "profile_banner_url": "https://pbs.twimg.com/profile_banners/892096112026427392/1501528207", "profile_link_color": "1DA1F2", "profile_sidebar_border_color": "C0DEED", "profile_sidebar_fill_color": "DDEEF6", "profile_text_color": "333333", "profile_use_background_image": true, "has_extended_profile": true, "default_profile": true, "default_profile_image": false, "following": false, "follow_request_sent": false, "notifications": false, "translator_type": "none"}, "geo": null, "coordinates": null, "place": null, "contributors": null, "retweeted_status": {"created_at": "Tue Mar 19 07:29:57 +0000 2019", "id": 1107907042948321281, "id_str": "1107907042948321281", "full_text": "INFORMATION EUROPE 1 : le domicile du \"#giletjaune\" #\u00c9ric Drouet vandalis\u00e9 https://t.co/rZvy2mgcuj", "truncated": false, "display_text_range": [0, 98], "entities": {"hashtags": [{"text": "giletjaune", "indices": [39, 50]}, {"text": "\u00c9ric", "indices": [52, 57]}], "symbols": [], "user_mentions": [], "urls": [{"url": "https://t.co/rZvy2mgcuj", "expanded_url": "https://www.europe1.fr/faits-divers/information-europe-1-le-domicile-du-gilet-jaune-eric-drouet-vandalise-3876593", "display_url": "europe1.fr/faits-divers/i\u2026", "indices": [75, 98]}]}, "metadata": {"iso_language_code": "fr", "result_type": "recent"}, "source": "<a href=\"http://twitter.com/download/iphone\" rel=\"nofollow\">Twitter for iPhone</a>", "in_reply_to_status_id": null, "in_reply_to_status_id_str": null, "in_reply_to_user_id": null, "in_reply_to_user_id_str": null, "in_reply_to_screen_name": null, "user": {"id": 1043410125774626816, "id_str": "1043410125774626816", "name": "\ud83c\udf0e ActuWorld \ud83c\udf0d", "screen_name": "actu_phone", "location": "Paris, France", "description": "\ud83c\udf0eActualit\u00e9 du jour\ud83c\udf0dRegroupement d\u2019informations journali\u00e8res", "url": "https://t.co/dSUgYO60Nn", "entities": {"url": {"urls": [{"url": "https://t.co/dSUgYO60Nn", "expanded_url": "https://www.youtube.com/c/Fastproduction", "display_url": "youtube.com/c/Fastproducti\u2026", "indices": [0, 23]}]}, "description": {"urls": []}}, "protected": false, "followers_count": 4042, "friends_count": 3381, "listed_count": 4, "created_at": "Sat Sep 22 08:02:14 +0000 2018", "favourites_count": 7, "utc_offset": null, "time_zone": null, "geo_enabled": false, "verified": false, "statuses_count": 19639, "lang": "fr", "contributors_enabled": false, "is_translator": false, "is_translation_enabled": false, "profile_background_color": "000000", "profile_background_image_url": "http://abs.twimg.com/images/themes/theme1/bg.png", "profile_background_image_url_https": "https://abs.twimg.com/images/themes/theme1/bg.png", "profile_background_tile": false, "profile_image_url": "http://pbs.twimg.com/profile_images/1092496479502127105/PvOWvWuc_normal.jpg", "profile_image_url_https": "https://pbs.twimg.com/profile_images/1092496479502127105/PvOWvWuc_normal.jpg", "profile_banner_url": "https://pbs.twimg.com/profile_banners/1043410125774626816/1549306799", "profile_link_color": "1B95E0", "profile_sidebar_border_color": "000000", "profile_sidebar_fill_color": "000000", "profile_text_color": "000000", "profile_use_background_image": false, "has_extended_profile": false, "default_profile": false, "default_profile_image": false, "following": false, "follow_request_sent": false, "notifications": false, "translator_type": "none"}, "geo": null, "coordinates": null, "place": null, "contributors": null, "is_quote_status": false, "retweet_count": 6, "favorite_count": 2, "favorited": false, "retweeted": false, "possibly_sensitive": false, "lang": "fr"}, "is_quote_status": false, "retweet_count": 6, "favorite_count": 0, "favorited": false, "retweeted": false, "possibly_sensitive": false, "lang": "fr"}